README.md
rumrunner.py
setup.py
rumrunner.egg-info/PKG-INFO
rumrunner.egg-info/SOURCES.txt
rumrunner.egg-info/dependency_links.txt
rumrunner.egg-info/requires.txt
rumrunner.egg-info/top_level.txt