Metadata-Version: 1.1
Name: rumrunner
Version: 0.6.1
Summary: Client to send metrics to Speakeasy server
Home-page: https://github.com/etdub/rumrunner
Author: Eric Wong
Author-email: UNKNOWN
License: Apache License 2.0
Platform: UNKNOWN
Classifier: Intended Audience :: Developers
Classifier: Natural Language :: English
Classifier: Programming Language :: Python
Classifier: Programming Language :: Python :: 2.7
Classifier: Programming Language :: Python :: 3
Classifier: Programming Language :: Python :: 3.3
Classifier: License :: OSI Approved :: Apache Software License
